djantic/__init__.py
djantic/fields.py
djantic/main.py
djantic/py.typed
tests/__init__.py
tests/test_fields.py
tests/test_files.py
tests/test_main.py
tests/test_multiple_level_relations.py
tests/test_queries.py
tests/test_relations.py
tests/test_schemas.py
tests/testapp/__init__.py
tests/testapp/apps.py
tests/testapp/fields.py
tests/testapp/manage.py
tests/testapp/models.py
tests/testapp/order.py
tests/testapp/settings.py
tests/testapp/project/__init__.py
tests/testapp/project/asgi.py
tests/testapp/project/settings.py
tests/testapp/project/urls.py
tests/testapp/project/wsgi.py
djantic2-1.0.5.dist-info/LICENSE
djantic2-1.0.5.dist-info/METADATA
djantic2-1.0.5.dist-info/WHEEL
djantic2-1.0.5.dist-info/top_level.txt
djantic2-1.0.5.dist-info/RECORD
